SpaGFT/__init__.py
SpaGFT/gft.py
SpaGFT/plot.py
SpaGFT/utils.py
SpaGFT-0.1.3.dist-info/LICENSE
SpaGFT-0.1.3.dist-info/METADATA
SpaGFT-0.1.3.dist-info/WHEEL
SpaGFT-0.1.3.dist-info/top_level.txt
SpaGFT-0.1.3.dist-info/RECORD
